odoo/addons/website_conditional_visibility_user_group/README.rst
odoo/addons/website_conditional_visibility_user_group/__init__.py
odoo/addons/website_conditional_visibility_user_group/__manifest__.py
odoo/addons/website_conditional_visibility_user_group/i18n/es.po
odoo/addons/website_conditional_visibility_user_group/i18n/it.po
odoo/addons/website_conditional_visibility_user_group/i18n/website_conditional_visibility_user_group.pot
odoo/addons/website_conditional_visibility_user_group/models/__init__.py
odoo/addons/website_conditional_visibility_user_group/models/ir_http.py
odoo/addons/website_conditional_visibility_user_group/readme/CONFIGURE.md
odoo/addons/website_conditional_visibility_user_group/readme/CONTRIBUTORS.md
odoo/addons/website_conditional_visibility_user_group/readme/DESCRIPTION.md
odoo/addons/website_conditional_visibility_user_group/static/description/icon.png
odoo/addons/website_conditional_visibility_user_group/static/description/index.html
odoo/addons/website_conditional_visibility_user_group/static/src/js/inject_dom.esm.js
odoo/addons/website_conditional_visibility_user_group/static/src/tests/snippet_visibility_portal_tests.esm.js
odoo/addons/website_conditional_visibility_user_group/static/src/tests/snippet_visibility_tests.esm.js
odoo/addons/website_conditional_visibility_user_group/tests/__init__.py
odoo/addons/website_conditional_visibility_user_group/tests/test_conditional_visibility_user_group.py
odoo/addons/website_conditional_visibility_user_group/views/snippet_options_template.xml
odoo_addon_website_conditional_visibility_user_group-17.0.1.0.0.4.dist-info/METADATA
odoo_addon_website_conditional_visibility_user_group-17.0.1.0.0.4.dist-info/WHEEL
odoo_addon_website_conditional_visibility_user_group-17.0.1.0.0.4.dist-info/top_level.txt
odoo_addon_website_conditional_visibility_user_group-17.0.1.0.0.4.dist-info/RECORD
